hello_thruster/__init__.py
jd_mlops-99.99.99.dist-info/METADATA
jd_mlops-99.99.99.dist-info/WHEEL
jd_mlops-99.99.99.dist-info/top_level.txt
jd_mlops-99.99.99.dist-info/RECORD
